discordrpc/__init__.py
discordrpc/baseclient.py
discordrpc/client.py
discordrpc/exceptions.py
discordrpc/payloads.py
discordrpc/presence.py
discordrpc/utils.py
discordrich-0.0.1.dist-info/LICENCE
discordrich-0.0.1.dist-info/METADATA
discordrich-0.0.1.dist-info/WHEEL
discordrich-0.0.1.dist-info/top_level.txt
discordrich-0.0.1.dist-info/RECORD
