Metadata-Version: 2.1
Name: discordrich
Version: 0.0.1
Summary: A Discord Rich Presence library
Home-page: https://git.10302170.tech/
Author: Ulif Systems
Author-email: donnierupp6@gmail.com
Project-URL: DiscordRich Website, https://ulifsystems.neocities.org/rpc
Classifier: Programming Language :: Python :: 3
Classifier: License :: OSI Approved :: MIT License
Classifier: Operating System :: OS Independent
Requires-Python: >=3.6
License-File: LICENCE
